sourmash_plugin_sketchall.py
sourmash_plugin_sketchall-0.2.2.dist-info/LICENSE
sourmash_plugin_sketchall-0.2.2.dist-info/METADATA
sourmash_plugin_sketchall-0.2.2.dist-info/WHEEL
sourmash_plugin_sketchall-0.2.2.dist-info/entry_points.txt
sourmash_plugin_sketchall-0.2.2.dist-info/top_level.txt
sourmash_plugin_sketchall-0.2.2.dist-info/RECORD
